Metadata-Version: 2.0
Name: odoo9-addon-stock-cycle-count
Version: 9.0.1.2.0
Summary: Adds the capability to schedule cycle counts in a warehouse through different rules defined by the user
Home-page: https://github.com/OCA/stock-logistics-warehouse
Author: Eficent, Odoo Community Association (OCA)
Author-email: support@odoo-community.org
License: AGPL-3
Platform: UNKNOWN
Classifier: Programming Language :: Python
Classifier: Framework :: Odoo
Classifier: License :: OSI Approved :: GNU Affero General Public License v3
Requires-Python: ~=2.7
Requires-Dist: numpy
Requires-Dist: odoo (<9.1a,>=9.0a)
Requires-Dist: odoo9-addon-stock-inventory-discrepancy
Requires-Dist: odoo9-addon-stock-inventory-exclude-sublocation
